{
	"next_topic_id": 4,
	"topic": [
		{
			"topic_id": 1,
			"title": "不太會用咯？有大神截圖教程或者是視頻教程嗎？",
			"body": "拜託",
			"parent_topic_uri": "12_1NV87VmSkezRyz8NbFpdkYJsJUSfXx7LJa",
			"added": 1460823559
		},
		{
			"topic_id": 2,
			"title": "推 倒了應該這個或者是G+更能替代",
			"body": "",
			"parent_topic_uri": "12_1NV87VmSkezRyz8NbFpdkYJsJUSfXx7LJa",
			"added": 1460823777
		},
		{
			"topic_id": 3,
			"title": "关于电视的问题和求助",
			"body": "最近在找电视软件可以看港澳台电视有没有破解版的？或者有什么方法可以很流畅的 ？？",
			"added": 1462032820,
			"parent_topic_uri": "19_1NV87VmSkezRyz8NbFpdkYJsJUSfXx7LJa"
		}
	],
	"topic_vote": {},
	"next_comment_id": 18,
	"comment": {
		"13_1NwWoM1qGUV9gjLG7QGyhqsRxKKga2rhtf": [
			{
				"comment_id": 1,
				"body": "上面什麼都是匿名？",
				"added": 1460824239
			}
		],
		"2_1jc2JUijhCn7BLf7Bf9mQa26a5wiT5S9N": [
			{
				"comment_id": 2,
				"body": "其實還有一種twister也不錯的  性質和twitter一樣  不過沒有twitter好",
				"added": 1460903596
			},
			{
				"comment_id": 9,
				"body": "覺得你說所言甚是。。但能有facebook twitter  某吧這樣集於一身功能的而且粘量很高的論壇很少   幾乎沒有覺得那個出色。",
				"added": 1460947037
			}
		],
		"2_1DRoM19XBUxtoRY2PwKQmuzbFSeoecmXrQ": [
			{
				"comment_id": 3,
				"body": "玩這個可以挖礦嗎？",
				"added": 1460903695
			}
		],
		"1_15RzGDnzJD4sUKbL4FgiMG8ULi69qGbyvh": [
			{
				"comment_id": 4,
				"body": "是不是？",
				"added": 1460905049
			}
		],
		"2_1CpQAAfxYtFqAGfoGd6gdaN6jerQGoknzV": [
			{
				"comment_id": 5,
				"body": "怎麼設置",
				"added": 1460905727
			}
		],
		"2_1uAAHfQZGERmS53bcbrnpgAMgpAqb7aEW": [
			{
				"comment_id": 6,
				"body": "建起來容易後面運行很重要，",
				"added": 1460905930
			}
		],
		"1_157d61UG24B66Yw2qwEQWY7yFAWp1HoAST": [
			{
				"comment_id": 7,
				"body": "不討論哪裡會強大？所有必須有看有說 無聊天不論壇",
				"added": 1460906113
			}
		],
		"1_1Kqvsi5cBGDUGi8Y47MkziFQnjuw1sDgpX": [
			{
				"comment_id": 8,
				"body": "像慧聰網",
				"added": 1460906848
			}
		],
		"1_1NvuCEiBua5qhzxkBcgP5rd6iUtZ8goVuJ": [
			{
				"comment_id": 10,
				"body": "要是有圖文並茂更好  我等小白看不懂！！！",
				"added": 1460947132
			}
		],
		"1_13Z7XxTa7JuFat3KzzMWu3onwM6biLuurJ": [
			{
				"comment_id": 11,
				"body": "> [hsuan](#comment_2_18AFgFJtWu6HbG5RmKc9WXdrrSxtAdg5w3): users.json这个文件的内容是否会更改？ 也就是说备份一次就可以了还是需要时时备份？\n\n這個相當於你的密碼",
				"added": 1461030732
			},
			{
				"comment_id": 15,
				"body": "小白看不懂 不知道怎麼設置",
				"added": 1461155735
			}
		],
		"17_13Z7XxTa7JuFat3KzzMWu3onwM6biLuurJ": [
			{
				"comment_id": 12,
				"body": "可以手把手教嗎？小白什麼都不懂",
				"added": 1461073543
			},
			{
				"comment_id": 13,
				"body": "可以手把手教嗎？小白什麼都不懂",
				"added": 1461073624
			}
		],
		"5_1DzpF7398yNGjFwHQqHAu9fRkbE3WZ6dZA": [
			{
				"comment_id": 14,
				"body": "這是基本版  不過還有很多沒有。",
				"added": 1461073750
			}
		],
		"16_1NwWoM1qGUV9gjLG7QGyhqsRxKKga2rhtf": [
			{
				"comment_id": 16,
				"body": "> [p2p](#comment_330_13Z7XxTa7JuFat3KzzMWu3onwM6biLuurJ): 虚拟机，专门玩弄病毒\n\n可以给个教程怎么搞虚拟机吗？",
				"added": 1462033356
			}
		],
		"1_1ATwnnMmnWF2NWdaEBDMxzjFNMghixLBKE": [
			{
				"comment_id": 17,
				"body": "最愛草榴的浮世繪。。。",
				"added": 1462461083
			}
		]
	},
	"comment_vote": {}
}