{
	"next_topic_id": 1,
	"topic": [],
	"topic_vote": {},
	"next_comment_id": 2,
	"comment": {
		"1_16qagSTV2hzZxmzwRL7xeLWYFfEQxxyq3y": [
			{
				"comment_id": 1,
				"body": "3.8.0.2版:breakwa11\n3.8.0.3版:CFGE\n3.8.0.4版:ACG3201660CG3\n3.8.0.5版:EB1C3hlF1605LM37.5G\n3.8.0.6版:cB1C3HAAPL160603C001000001421M37.5G\n3.8.0.7版:cB1C3HAAPL160603C001000003288M37.5GF529E10D\n3.8.1版:7/16HD1718575780564841506C4\n3.8.1.2版:2Q10529.97BW17Meow40G413403A4A364D5",
				"added": 1465906367
			}
		]
	},
	"comment_vote": {}
}