{
	"next_topic_id": 1,
	"topic": [],
	"topic_vote": {
		"3_16XhwuR6w5BURDK4bn3m3Fy9qXRmX24kDc": 1
	},
	"next_comment_id": 4,
	"comment": {
		"1_13Z7XxTa7JuFat3KzzMWu3onwM6biLuurJ": [
			{
				"comment_id": 1,
				"body": "留名",
				"added": 1461678984
			}
		],
		"1_1C9W8CQ4omougnEsbhman5RAe83YM76R6Q": [
			{
				"comment_id": 2,
				"body": "求源码密码,381,3811都得",
				"added": 1464099310
			},
			{
				"comment_id": 3,
				"body": "> [breakwa11](#comment_40_16XhwuR6w5BURDK4bn3m3Fy9qXRmX24kDc): 源代码密码和下载包的密码相同\n\n好像381的源码的解压密码跟软件的解压密码并不一致,也可能是我下载的源码有问题",
				"added": 1464156809
			}
		]
	},
	"comment_vote": {}
}