{
	"next_topic_id": 2,
	"topic": [
		{
			"topic_id": 1,
			"title": "е¶ВдљХиГљдЄАеК≥ж∞ЄйАЄзЪДжґИзБ≠зїњзїњпЉЯ",
			"body": "жДЯиІЙзО∞еЬ®зїњзїњжШѓеЕ®зРГжЬАдЄНз®≥еЃЪеЫ†зі†пЉМе§ІеЃґжЭ•еїЇи®АзМЃз≠ЦпЉМжОҐиЃ®дЄЛе¶ВдљХжґИзБ≠зїњзїњгАВ",
			"added": 1461565489,
			"parent_topic_uri": "11_1NV87VmSkezRyz8NbFpdkYJsJUSfXx7LJa"
		}
	],
	"topic_vote": {},
	"next_comment_id": 6,
	"comment": {
		"2_1uAAHfQZGERmS53bcbrnpgAMgpAqb7aEW": [
			{
				"comment_id": 1,
				"body": "жИСдїђеЬ®еЕ≥ж≥®дЄ≠рЯШД",
				"added": 1461048428
			}
		],
		"1_1CmvZKfajUJh5TPFiXbw4RnxA88YzgR11b": [
			{
				"comment_id": 2,
				"body": "> [timeout](#comment_56_1NwWoM1qGUV9gjLG7QGyhqsRxKKga2rhtf): дЄНи¶БзЩЉдЇВеАЂзЪДжЭ±и•њ~дЄНи¶БзЩЉдЇВеАЂзЪДжЭ±и•њ~дЄНи¶БзЩЉдЇВеАЂзЪДжЭ±и•њ~дЄНи¶БзЩЉдЇВеАЂзЪДжЭ±и•њ~дЄНи¶БзЩЉдЇВеАЂзЪДжЭ±и•њ~дЄНи¶БзЩЉдЇВеАЂзЪДжЭ±и•њ~дЄНи¶БзЩЉдЇВеАЂзЪДжЭ±и•њ~дЄНи¶БзЩЉдЇВеАЂзЪДжЭ±и•њ~дЄНи¶БзЩЉдЇВеАЂзЪДжЭ±и•њ~дЄНи¶БзЩЉдЇВеАЂзЪДжЭ±и•њ~дЄНи¶БзЩЉдЇВеАЂзЪДжЭ±и•њ~дЄНи¶БзЩЉдЇВеАЂзЪДжЭ±и•њ~дЄНи¶БзЩЉдЇВеАЂзЪДжЭ±и•њ~дЄНи¶БзЩЉдЇВеАЂзЪДжЭ±и•њ~дЄНи¶БзЩЉдЇВеАЂзЪДжЭ±и•њ~дЄНи¶БзЩЉдЇВеАЂзЪДжЭ±и•њ~дЄНи¶БзЩЉдЇВеАЂзЪДжЭ±и•њ~дЄНи¶БзЩЉдЇВеАЂзЪДжЭ±и•њ~дЄНи¶БзЩЉдЇВеАЂзЪДжЭ±и•њ~дЄНи¶БзЩЉдЇВеАЂзЪДжЭ±и•њ~дЄНи¶БзЩЉдЇВеАЂзЪДжЭ±и•њ~дЄНи¶БзЩЉдЇВеАЂзЪДжЭ±и•њ~дЄНи¶БзЩЉдЇВеАЂзЪДжЭ±и•њ~дЄНи¶БзЩЉдЇВеАЂзЪДжЭ±и•њ~дЄНи¶БзЩЉдЇВеАЂзЪДжЭ±и•њ~дЄНи¶БзЩЉдЇВеАЂзЪДжЭ±и•њ~дЄНи¶БзЩЉдЇВеАЂзЪДжЭ±и•њ~дЄНи¶БзЩЉдЇВеАЂзЪДжЭ±и•њ~дЄНи¶БзЩЉдЇВеАЂзЪДжЭ±и•њ~дЄНи¶БзЩЉдЇВеАЂзЪДжЭ±и•њ~дЄНи¶БзЩЉдЇВеАЂзЪДжЭ±и•њ~дЄНи¶БзЩЉдЇВеАЂзЪДжЭ±и•њ~дЄНи¶БзЩЉдЇВеАЂзЪДжЭ±и•њ~дЄНи¶БзЩЉдЇВеАЂзЪДжЭ±и•њ~дЄНи¶БзЩЉдЇВеАЂзЪДжЭ±и•њ~дЄНи¶БзЩЉдЇВеАЂзЪДжЭ±и•њ~дЄНи¶БзЩЉдЇВеАЂзЪДжЭ±и•њ~дЄНи¶БзЩЉдЇВеАЂзЪДжЭ±и•њ~дЄНи¶БзЩЉдЇВеАЂзЪДжЭ±и•њ~дЄНи¶БзЩЉдЇВеАЂзЪДжЭ±и•њ~дЄНи¶БзЩЉдЇВеАЂзЪДжЭ±и•њ~дЄНи¶БзЩЉдЇВеАЂзЪДжЭ±и•њ~дЄНи¶БзЩЉдЇВеАЂзЪДжЭ±и•њ~дЄНи¶БзЩЉдЇВеАЂзЪДжЭ±и•њ~дЄНи¶БзЩЉдЇВеАЂзЪДжЭ±и•њ~дЄНи¶БзЩЉдЇВеАЂзЪДжЭ±и•њ~дЄНи¶БзЩЉдЇВеАЂзЪДжЭ±и•њ~дЄНи¶БзЩЉдЇВеАЂзЪДжЭ±и•њ~дЄНи¶БзЩЉдЇВеАЂзЪДжЭ±и•њ~дЄНи¶БзЩЉдЇВеАЂзЪДжЭ±и•њ~дЄНи¶БзЩЉдЇВеАЂзЪДжЭ±и•њ~дЄНи¶БзЩЉдЇВеАЂзЪДжЭ±и•њ~дЄНи¶БзЩЉдЇВеАЂзЪДжЭ±и•њ~дЄНи¶БзЩЉдЇВеАЂзЪДжЭ±и•њ~дЄНи¶БзЩЉдЇВеАЂзЪДжЭ±и•њ~дЄНи¶БзЩЉдЇВеАЂзЪДжЭ±и•њ~дЄНи¶БзЩЉдЇВеАЂзЪДжЭ±и•њ~дЄНи¶БзЩЉдЇВеАЂзЪДжЭ±и•њ~дЄНи¶БзЩЉдЇВеАЂзЪДжЭ±и•њ~дЄНи¶БзЩЉдЇВеАЂзЪДжЭ±и•њ~\n\nе∞ПжЬЛеПЛеРЧпЉЯ",
				"added": 1461048787
			}
		],
		"1_1BQdzfUgn396CeghTX6j9T29UfngxzYfXB": [
			{
				"comment_id": 3,
				"body": "еЇФиѓ•жШѓ",
				"added": 1461050586
			}
		],
		"1_197rZZrY6sHsYEQ9U1bJEq51M6R4oyhRRS": [
			{
				"comment_id": 4,
				"body": "жИСињЩssдєЯж≤°йЧЃйҐШеХК",
				"added": 1461122607
			}
		],
		"8_12kgNNnBaR3s7bN761BCQtkzSC7EbrK2Jd": [
			{
				"comment_id": 5,
				"body": "жѓФзЙєеЄБжФѓдїШе•љдЇЖ",
				"added": 1461136249
			}
		]
	},
	"comment_vote": {
		"4_1KxqVQW8N2Yc38LRTxZb73UkNj7s2FftGy": 1
	}
}