{
	"next_topic_id": 1,
	"topic": [],
	"topic_vote": {},
	"next_comment_id": 4,
	"comment": {
		"1_1NZsz5ugkzg27d9jmc8qrT9GxcLZdiuBGP": [
			{
				"comment_id": 1,
				"body": "新疆已习惯",
				"added": 1462962429
			}
		],
		"1_1C9W8CQ4omougnEsbhman5RAe83YM76R6Q": [
			{
				"comment_id": 2,
				"body": "3.8.0.7密码……",
				"added": 1463493108
			}
		],
		"1_1471Xr4iRPN5dHHNo8fN31KrXwQ3xV9jJE": [
			{
				"comment_id": 3,
				"body": "有没有好的号，关注啊",
				"added": 1463667104
			}
		]
	},
	"comment_vote": {}
}