{
	"next_topic_id": 10,
	"topic": [
		{
			"topic_id": 1,
			"title": "ZeroNet地址如何绑定“.bit\"域名？",
			"body": "ZeroName网站有很多如下用Zero地址绑定的以“.bit\"结尾的网站，想问一下这是怎么实现的？希望有谁能提供一下中文教程，在这里多谢了。\nhttp://127.0.0.1:43110/1Name2NXVi1RDPDgf5617UoW7xA6YrhM9F/\n\nDOMAIN                 ADDRESS\t                                                                  NETWORK\n0activity.bit    \t15GAu5QYg34TLzD4b2WMpZSid9S2K6M54h\t• Namecoin\n\n这是Youtube上的教程：https://www.youtube.com/watch?v=IfVDZUX-0xk&list=PLgFqcJDOq2q5orC1U4IvDBMpjezKt-X4E&index=6",
			"added": 1461160435,
			"parent_topic_uri": "8_1NV87VmSkezRyz8NbFpdkYJsJUSfXx7LJa"
		},
		{
			"topic_id": 2,
			"title": "如何通过Tor网络匿名使用ZeroNet？",
			"body": "之所以写这个教程，是因为我没能通过几个流传的中文教程进入Tor网络。\nhttp://127.0.0.1:43110/fenxiang.bit/?Post:4:%E5%A6%82%E4%BD%95%E9%80%9A%E8%BF%87Tor%E7%BD%91%E7%BB%9C%E5%8C%BF%E5%90%8D%E4%BD%BF%E7%94%A8ZeroNet%EF%BC%9F",
			"added": 1461660794,
			"parent_topic_uri": "8_1NV87VmSkezRyz8NbFpdkYJsJUSfXx7LJa"
		},
		{
			"topic_id": 3,
			"title": "发现注册“.bit”域名时，包含大写字母不能解析到相应ZeroNet地址。",
			"body": "我注册的域名：Somthing.bit不能解析到0Net地址：1t6o5BVyJrSAtFGoXUkjfjCNyhyH8VcfT\nfenxiang.bit却可以，再但个是，0Net官网就行：ZeroNetwork.bit\n各位，谁知道原因？",
			"added": 1461747910,
			"parent_topic_uri": "8_1NV87VmSkezRyz8NbFpdkYJsJUSfXx7LJa"
		},
		{
			"topic_id": 4,
			"title": "零网中文教学 wiki - 编程随想之友 \".bit\"域名：http://127.0.0.1:43110/wikicn.bit",
			"body": "个人认为网站需要改进一下交互逻辑。\n比如：\n既然是关于ONet的教学wiki，打开网站就应该直观呈现教学内容，而不是“**这是由@am630 设立的的小型维基网站，目的明确【零网中文教学】。编程随想是一位匿名的程序员，而am630 则是【编程随想之友】。**”\n最好能统一markdown格式。\n抛板儿砖引玉吧！",
			"added": 1461756662,
			"parent_topic_uri": "8_1NV87VmSkezRyz8NbFpdkYJsJUSfXx7LJa"
		},
		{
			"topic_id": 5,
			"title": "同一“.bit”域名下如何绑定多个IP地址？——这是个问题。",
			"body": "how？",
			"added": 1461757368,
			"parent_topic_uri": "8_1NV87VmSkezRyz8NbFpdkYJsJUSfXx7LJa"
		},
		{
			"topic_id": 6,
			"title": "如何在Namecoin 客户端导入钱包文件？",
			"body": "不知道，请教！",
			"added": 1462115747,
			"parent_topic_uri": "19_1NV87VmSkezRyz8NbFpdkYJsJUSfXx7LJa"
		},
		{
			"topic_id": 7,
			"title": "IPFS 分布式文件系统中文版教程？——这是问题。",
			"body": "0net结合IPFS，想想挺激动。",
			"added": 1462330999,
			"parent_topic_uri": "19_1NV87VmSkezRyz8NbFpdkYJsJUSfXx7LJa"
		},
		{
			"topic_id": 8,
			"title": "如何实现Onet地址只需输入“.bit”域名而不用加前缀“127.0.0.1：43110”？——这是问题。",
			"body": "",
			"added": 1462333731,
			"parent_topic_uri": "8_1NV87VmSkezRyz8NbFpdkYJsJUSfXx7LJa"
		},
		{
			"topic_id": 9,
			"title": "一个匿名文件分享工具：demonsaw",
			"body": "官网：https://www.demonsaw.com/\n目前使用的人还比较少，有谁能从技术细节讲讲它是怎么实现的吗？",
			"added": 1463494841,
			"parent_topic_uri": "19_1NV87VmSkezRyz8NbFpdkYJsJUSfXx7LJa"
		}
	],
	"topic_vote": {
		"25_13Z7XxTa7JuFat3KzzMWu3onwM6biLuurJ": 1
	},
	"next_comment_id": 9,
	"comment": {
		"5_18kDuSDb2D5QTtabXj6Ert7dTvnUA3FSHN": [
			{
				"comment_id": 1,
				"body": "不知道为什么，自己在namecoin qt客户端绑定zeronet地址后，不能使用注册的域名。再等等看。",
				"added": 1461300636
			},
			{
				"comment_id": 2,
				"body": "> [1iv1n](#comment_1_1167YzSjQX87VWthf4KxKSYK55j6duccdM): 你的 mydf.bit 是花钱注册的？？\n\n注册域名很便宜的，只要0.002NMC。目前2.72RMB兑1个NMC。",
				"added": 1461300870
			}
		],
		"11_1Q7UWk3im88kJkzmhzfD5q44rQDXLatxYq": [
			{
				"comment_id": 3,
				"body": "对，你首先得备份钱包。",
				"added": 1461644765
			}
		],
		"5_14kpMFXkLerqtvXM9rywW8h7rdLEBYz9FS": [
			{
				"comment_id": 4,
				"body": "> [petercxy](#comment_24_1DXR2Di8Ks9JijfNycWErpenoxxchrdWBB): ZeroNet 上的域名是不绑定IP的啦。。\n应该是可以的，这两个个网站：http://testnet.explorer.bit/ http://explorer.bit/ 可以直接打开——前提是使用支持解析“.bit”的DNS，如：https://www.opennicproject.org/",
				"added": 1461760533
			},
			{
				"comment_id": 5,
				"body": "> [petercxy](#comment_26_1DXR2Di8Ks9JijfNycWErpenoxxchrdWBB): 这样的域名就不属于 ZeroNet 了。。我说的是 ZeroNet 上的。\n\n你先入为主了，没认真看问题。",
				"added": 1461763322
			},
			{
				"comment_id": 6,
				"body": "> [petercxy](#comment_27_1DXR2Di8Ks9JijfNycWErpenoxxchrdWBB): 然而你发在了 ZeroNet 讨论板块上，我就自动认为是 ZeroNet 啦 = = 至于如何绑定多个IP，这不是要看DNS服务么。\n\n不知道对不对，我觉得只要DNS服务器支持解析“.bit”域名，就不需要提供DNS解析的服务了。",
				"added": 1461767632
			}
		],
		"6_14kpMFXkLerqtvXM9rywW8h7rdLEBYz9FS": [
			{
				"comment_id": 7,
				"body": "自己回答吧！是非人性化的复制粘贴。\n首先，找到Namecoin钱包，地址为：C:\\Users\\你的windows用户名\\AppData\\Roaming\\Namecoin；\n然后，重命名你备份的钱包文件为“wallet.dat”，并将其复制到上面路径中，替换原默认钱包同名文件。\n参考：https://forum.namecoin.info/viewtopic.php?f=2&t=1717",
				"added": 1462201112
			}
		],
		"9_14kpMFXkLerqtvXM9rywW8h7rdLEBYz9FS": [
			{
				"comment_id": 8,
				"body": "> [riccardo](#comment_46_1HK5C3Uf8zvbbSb92ZP6EsfHKC59MXDcK9): 这个有什么需求？\n\n解压就能用",
				"added": 1463532577
			}
		]
	},
	"comment_vote": {}
}