{
	"next_topic_id": 1,
	"topic": [],
	"topic_vote": {},
	"next_comment_id": 4,
	"comment": {
		"1_1C9W8CQ4omougnEsbhman5RAe83YM76R6Q": [
			{
				"comment_id": 1,
				"body": "> [22dm](#comment_1_1H6KGkRVJnC7FiAxkz8ZSvsBvqDugtMDaP): 3.8.0.7密码cB1C3HAAPL160603C001000003288M37.5GF529E10D下方为硬币问题的mathematica代码For[t = 0, 1 - Last[With[{nn = 10}, LinearRecurrence[Table[1, {nn}], Join[Table[0, {nn - 1}], {1}], t + 11]]]/2^t < 0.8, t++];Print[t]输出为3288\n\n牛逼...",
				"added": 1463531851
			}
		],
		"1_1HWmhDrqVNGsr7ExD8G5EJS49NJRH1nKAn": [
			{
				"comment_id": 2,
				"body": "点 SSR 链接会显示，更新前看更新日志啊...",
				"added": 1471499496
			}
		],
		"1_19sjUkvu2KTzd8DTwftTBtUmUqVKsA1iyf": [
			{
				"comment_id": 3,
				"body": "围棋这个确实不会啊.....",
				"added": 1472195546
			}
		]
	},
	"comment_vote": {}
}